bytetree/__init__.py
bytetree/hello.py
bytetree-0.0.1.dist-info/METADATA
bytetree-0.0.1.dist-info/WHEEL
bytetree-0.0.1.dist-info/licenses/LICENSE
bytetree-0.0.1.dist-info/RECORD
