Metadata-Version: 2.4
Name: bytetree
Version: 0.0.1
Summary: bytetree tools package
Project-URL: Homepage, https://bytetree-ai.com
Author-email: jiquanbai <jiquanbai@bytetree.ai>
License-File: LICENSE
Classifier: License :: OSI Approved :: MIT License
Classifier: Operating System :: OS Independent
Classifier: Programming Language :: Python :: 3
Requires-Python: >=3.8
